{
    "@context": "https://schema.org",
    "@type": "Recipe",
    "name": "Chicken Taco Stew",
    "author": {
        "@type": "Person",
        "name": "Sue Dunn"
    },
    "description": "description of recipe",
    "recipeCategory": "soups",
    "recipeYield": "yield",
    "recipeIngredient": [
        "1 onion, chopped",
        "1 (16 oz) can cannellini beans, drained and rinsed",
        "1 (16 oz) can black beans, drained and rinsed",
		"1 (16 oz) can sweet corn, drained",
        "3 (10 oz) cans of diced tomatoes with green chillies",
        "1 packet taco seasoning",
        "3 chicken breasts, cut lengthwise in half",
		"2 avocados",
		"sour cream"
    ],
    "recipeInstructions": [
        {
            "@type": "HowToStep",
            "text": "Mix everything together in a slow cooker except chicken. Lay chicken on top and cover. Cook on low for 6-8 hours or on high for 4 hours."
        },
        {
            "@type": "HowToStep",
            "text": "30 minutes before serving, remove chicken and shred. Return shredded chicken to slow cooker and stir in. Serve with sour cream and avocado."
        }
	],
    "image": [
        "/home/tim/Documents/projects/recipes/img/taco_stew.jpg"
    ]
}
