{
    "@context": "https://schema.org",
    "@type": "Recipe",
    "name": "Seared Chicken With Avocado",
    "author": {
        "@type": "Person",
        "name": "allrecipes.com"
    },
    "description": "description of recipe",
    "recipeCategory": "chicken",
    "recipeYield": "yield",
    "recipeIngredient": [
        "1 1/2 tsp blackened seasoning",
        "4 (4 oz) skinless, boneless chicken breast halves",
        "1 tsp olive oil",
        "1 diced, peeled avocado",
        "2 Tbsp chopped fresh cilantro",
        "1 jalapeno pepper, seeded and finely chopped",
        "2 Tbsp freh lime juice (anout 1 lime)",
        "1/4 tsp salt",
        "1 lime, cut into quarters"
    ],
    "recipeInstructions": [
        {
            "@type": "HowToStep",
            "text": "Sprinkle seasoning on both sides of chicken"
        },
        {
            "@type": "HowToStep",
            "text": "Heat oil in a large nonstick skillet over high heat. Add chicken, smooth side down, to pan; cook 1 minute or until seared."
        },
        {
            "@type": "HowToStep",
            "text": "Reduce hate to medium; cook 3 minutes on each side or until lightly browned."
        },
        {
            "@type": "HowToStep",
            "text": "Combine avocado, cilantro, pepper, lime juice and salt."
        },
        {
            "@type": "HowToStep",
            "text": "Squeeze one-quarter lime over each piece of chicken before serving. Serve with avocado mixture."
        }
    ],
    "image": [
        "/home/tim/Documents/projects/recipes/img/F487A08A-06D4-4929-8018-9121063658C4.jpg"
    ]
}
